temperature2mqtt/__init__.py
temperature2mqtt/__main__.py
temperature2mqtt/temperature2mqtt.py
temperature2mqtt/temperatureReader.py
temperature2mqtt-0.1.0.dist-info/LICENSE
temperature2mqtt-0.1.0.dist-info/METADATA
temperature2mqtt-0.1.0.dist-info/WHEEL
temperature2mqtt-0.1.0.dist-info/top_level.txt
temperature2mqtt-0.1.0.dist-info/RECORD
